tests/__init__.py
tests/fileoperation_test.py
tests/getoperation_out_exception_test.py
tests/getoperation_span_test.py
tests/readoperation_in_exception_test.py
tests/readoperation_out_exception_test.py
xkye/__init__.py
xkye/xkye_model.py
xkye/libs/XkyeExtendedListener.py
xkye/libs/XkyeLexer.py
xkye/libs/XkyeListener.py
xkye/libs/XkyeParser.py
xkye/libs/__init__.py
xkye-1.0.1.dist-info/LICENSE
xkye-1.0.1.dist-info/METADATA
xkye-1.0.1.dist-info/WHEEL
xkye-1.0.1.dist-info/top_level.txt
xkye-1.0.1.dist-info/RECORD
