Metadata-Version: 2.1
Name: xkye
Version: 1.0.1
Summary: Official Python Standard Library for Xkye Language
Home-page: https://github.com/RahmanAnsari/
Author: Rahman Ansari
Author-email: iamrahmanansari@gmail.com
License: MIT License        
Platform: UNKNOWN
Classifier: Development Status :: 5 - Production/Stable
Classifier: Framework :: Pytest
Classifier: Intended Audience :: Developers
Classifier: License :: OSI Approved :: MIT License
Classifier: Natural Language :: English
Classifier: Operating System :: OS Independent
Classifier: Programming Language :: Python
Classifier: Topic :: Software Development :: Libraries :: Python Modules
License-File: LICENSE
Requires-Dist: antlr4-python3-runtime
Requires-Dist: multipledispatch
